raw2mzml
