Metadata-Version: 1.0
Name: raw2mzml
Version: 0.0.3
Summary: library and command line tool to convert Thermo Fisher raw files to mz(X)ML
Home-page: https://ssdmsource.ethz.ch/uweschmitt/raw2mzml/tree/master
Author: Uwe Schmitt
Author-email: uwe.schmitt@id.ethz.ch
License: http://opensource.org/licenses/BSD-3-Clause
Platform: win32
